app.py
database.py
Eeron-1.0.0.dist-info/LICENSE
Eeron-1.0.0.dist-info/METADATA
Eeron-1.0.0.dist-info/WHEEL
Eeron-1.0.0.dist-info/top_level.txt
Eeron-1.0.0.dist-info/RECORD
