Metadata-Version: 2.1
Name: Eeron
Version: 1.0.0
Summary: New organaizer module
Home-page: https://github.com/Cyrp48/Eeron/tree/maste
Author: cypr
Author-email: cyprcyrp@gmail.com
License: Copyright [2024] [cypr]
License-File: LICENSE
